{
  "frame_size": {
    "width": 768,
    "height": 432
  },
  "icon": {
    "default": {
      "my": {
        "min": {
          "x": 221,
          "y": 18
        },
        "max": {
          "x": 352,
          "y": 52
        }
      },
      "your": {
        "min": {
          "x": 416,
          "y": 18
        },
        "max": {
          "x": 545,
          "y": 52
        }
      }
    },
    "friend_pinch": {
      "my": {
        "min": {
          "x": 235,
          "y": 20
        },
        "max": {
          "x": 348,
          "y": 50
        }
      },
      "your": {
        "min": {
          "x": 414,
          "y": 17
        },
        "max": {
          "x": 560,
          "y": 53
        }
      }
    },
    "enemy_pinch": {
      "my": {
        "min": {
          "x": 207,
          "y": 17
        },
        "max": {
          "x": 350,
          "y": 53
        }
      },
      "your": {
        "min": {
          "x": 418,
          "y": 21
        },
        "max": {
          "x": 533,
          "y": 50
        }
      }
    }
  }
}